aws_hcs_cli/__init__.py
aws_hcs_cli/_azure_cloud_mfa_authenticator.py
aws_hcs_cli/_azure_mfa_authenticator.py
aws_hcs_cli/_duo_authenticator.py
aws_hcs_cli/_duo_universal_prompt_authenticator.py
aws_hcs_cli/_rsa_authenticator.py
aws_hcs_cli/_symantec_vip_access.py
aws_hcs_cli/_version.py
aws_hcs_cli/account_aliases_fetcher.py
aws_hcs_cli/authenticator.py
aws_hcs_cli/commands.py
aws_hcs_cli/consts.py
aws_hcs_cli/helpers.py
aws_hcs_cli/html_roles_fetcher.py
aws_hcs_cli/list_profiles.py
aws_hcs_cli/login.py
aws_hcs_cli/prepare.py
aws_hcs_cli/reset.py
aws_hcs_cli/role_chooser.py
aws_hcs_cli/roles_assertion_extractor.py
aws_hcs_cli-6.4.1.dist-info/entry_points.txt
aws_hcs_cli-6.4.1.dist-info/LICENSE
aws_hcs_cli-6.4.1.dist-info/METADATA
aws_hcs_cli-6.4.1.dist-info/WHEEL
aws_hcs_cli-6.4.1.dist-info/RECORD
